stactools/noaa_mrms_qpe/__init__.py
stactools/noaa_mrms_qpe/cog.py
stactools/noaa_mrms_qpe/commands.py
stactools/noaa_mrms_qpe/constants.py
stactools/noaa_mrms_qpe/fileinfo.py
stactools/noaa_mrms_qpe/stac.py
stactools_noaa_mrms_qpe-0.3.1.dist-info/LICENSE
stactools_noaa_mrms_qpe-0.3.1.dist-info/METADATA
stactools_noaa_mrms_qpe-0.3.1.dist-info/WHEEL
stactools_noaa_mrms_qpe-0.3.1.dist-info/top_level.txt
stactools_noaa_mrms_qpe-0.3.1.dist-info/RECORD
