Metadata-Version: 2.1
Name: stactools-noaa-mrms-qpe
Version: 0.3.1
Summary: stactools package for NOAA''s Multi-Radar Multi-Sensor Quantitative Precipitation Estimation dataset
Home-page: https://github.com/stactools-packages/noaa-mrms-qpe
Author: Matthias Mohr
Author-email: matthias.mohr@radiant.earth
Project-URL: Issues, https://github.com/stactools-packages/noaa-mrms-qpe/issues
Keywords: stactools,noaa,mrms,qpe,STAC
Classifier: Development Status :: 4 - Beta
Classifier: License :: OSI Approved :: Apache Software License
Classifier: Programming Language :: Python :: 3.7
Classifier: Programming Language :: Python :: 3.8
Classifier: Programming Language :: Python :: 3.9
Classifier: Programming Language :: Python :: 3.10
License-File: LICENSE
Requires-Dist: python-dateutil (>=2.7.0)
Requires-Dist: types-python-dateutil (>=2.7.0)
Requires-Dist: stactools (>=0.3.1)
